y_trans/__init__.py
y_trans/translator.py
y_trans-0.0.2a0.data/scripts/y_trans
y_trans-0.0.2a0.dist-info/LICENSE
y_trans-0.0.2a0.dist-info/METADATA
y_trans-0.0.2a0.dist-info/WHEEL
y_trans-0.0.2a0.dist-info/top_level.txt
y_trans-0.0.2a0.dist-info/RECORD
